Classy/__init__.py
Classy/basic.py
Classy/functions.py
Classy/model.py
Classy/server.py
classy_ai-0.0.15.dist-info/licenses/LICENSE
classy_ai-0.0.15.dist-info/METADATA
classy_ai-0.0.15.dist-info/WHEEL
classy_ai-0.0.15.dist-info/top_level.txt
classy_ai-0.0.15.dist-info/RECORD
