Metadata-Version: 2.4
Name: Classy-AI
Version: 0.0.15
Summary: A python module that utilizes AI to classify natural language into categories for processing with other models.
Home-page: https://github.com/eedeb/Classy
Author: eedeb
Author-email: 123scoring@gmail.com
Classifier: Programming Language :: Python :: 3
License-File: LICENSE
Requires-Dist: torch
Requires-Dist: openai
Requires-Dist: numpy
Requires-Dist: Search-Scrape
Requires-Dist: nltk
Requires-Dist: sentence-transformers
Dynamic: author
Dynamic: author-email
Dynamic: classifier
Dynamic: description
Dynamic: description-content-type
Dynamic: home-page
Dynamic: license-file
Dynamic: requires-dist
Dynamic: summary
